source_intercom/__init__.py
source_intercom/components.py
source_intercom/manifest.yaml
source_intercom/run.py
source_intercom/source.py
source_intercom/spec.json
airbyte_source_intercom-0.8.3.dist-info/METADATA
airbyte_source_intercom-0.8.3.dist-info/WHEEL
airbyte_source_intercom-0.8.3.dist-info/entry_points.txt
airbyte_source_intercom-0.8.3.dist-info/RECORD
