Metadata-Version: 2.1
Name: airbyte-source-intercom
Version: 0.8.3
Summary: Source implementation for Intercom Yaml.
Home-page: https://airbyte.com
License: MIT
Author: Airbyte
Author-email: contact@airbyte.io
Requires-Python: >=3.10,<3.12
Classifier: License :: OSI Approved :: MIT License
Classifier: Programming Language :: Python :: 3
Classifier: Programming Language :: Python :: 3.10
Classifier: Programming Language :: Python :: 3.11
Requires-Dist: airbyte-cdk (>=4.5.4,<5.0.0)
Project-URL: Documentation, https://docs.airbyte.com/integrations/sources/intercom
Project-URL: Repository, https://github.com/airbytehq/airbyte
